pairwiseANIviz/__init__.py
pairwiseANIviz/get_args.py
pairwiseANIviz/pairwiseANI.py
pairwiseaniviz-1.3.dist-info/licenses/LICENSE
pairwiseaniviz-1.3.dist-info/METADATA
pairwiseaniviz-1.3.dist-info/WHEEL
pairwiseaniviz-1.3.dist-info/entry_points.txt
pairwiseaniviz-1.3.dist-info/top_level.txt
pairwiseaniviz-1.3.dist-info/RECORD
