Metadata-Version: 2.4
Name: pairwiseANIviz
Version: 1.3
Summary: Pairwise ANI (Average Nucleotide Identity) visualization tool
Home-page: https://github.com/RunJiaJi/pairwiseANIviz
Author: Runjia Ji
Author-email: jirunjia@gmail.com
Project-URL: Bug Reports, https://github.com/RunJiaJi/pairwiseANIviz/issues
Project-URL: Source, https://github.com/RunJiaJi/pairwiseANIviz
Project-URL: Documentation, https://github.com/RunJiaJi/pairwiseANIviz#readme
Keywords: bioinformatics,ANI,visualization,clustering,heatmap,microbiology
Classifier: Development Status :: 4 - Beta
Classifier: Intended Audience :: Science/Research
Classifier: Topic :: Scientific/Engineering :: Bio-Informatics
Classifier: License :: OSI Approved :: MIT License
Classifier: Programming Language :: Python :: 3
Classifier: Programming Language :: Python :: 3.7
Classifier: Programming Language :: Python :: 3.8
Classifier: Programming Language :: Python :: 3.9
Classifier: Programming Language :: Python :: 3.10
Classifier: Programming Language :: Python :: 3.11
Classifier: Operating System :: OS Independent
Requires-Python: >=3.7
License-File: LICENSE
Requires-Dist: pandas>=1.3.0
Requires-Dist: matplotlib>=3.5.0
Requires-Dist: seaborn>=0.11.0
Requires-Dist: scipy>=1.7.0
Dynamic: author
Dynamic: author-email
Dynamic: classifier
Dynamic: description
Dynamic: description-content-type
Dynamic: home-page
Dynamic: keywords
Dynamic: license-file
Dynamic: project-url
Dynamic: requires-dist
Dynamic: requires-python
Dynamic: summary
